pyrses/AsciiApp.py
pyrses/Controller.py
pyrses/Frame.py
pyrses/GenClass.py
pyrses/Page.py
pyrses/__init__.py
pyrses/pyrses.py
pyrses/start_app.py
pyrses/templ/base_app.yml
pyrses/templ/base_frame.yml
pyrses/templ/base_page.yml
pyrses/test/__init__.py
pyrses-0.0.2.dist-info/DESCRIPTION.rst
pyrses-0.0.2.dist-info/METADATA
pyrses-0.0.2.dist-info/RECORD
pyrses-0.0.2.dist-info/WHEEL
pyrses-0.0.2.dist-info/entry_points.txt
pyrses-0.0.2.dist-info/metadata.json
pyrses-0.0.2.dist-info/top_level.txt
